calculator_mcp_server.py
calculator_mcp_server_tang-0.1.3.dist-info/licenses/LICENSE
calculator_mcp_server_tang-0.1.3.dist-info/METADATA
calculator_mcp_server_tang-0.1.3.dist-info/WHEEL
calculator_mcp_server_tang-0.1.3.dist-info/entry_points.txt
calculator_mcp_server_tang-0.1.3.dist-info/top_level.txt
calculator_mcp_server_tang-0.1.3.dist-info/RECORD
