Metadata-Version: 2.4
Name: calculator-mcp-server-tang
Version: 0.1.3
Summary: 一个提供加减乘除计算功能的MCP服务器
Author-email: tangyongkang <316674908@qq.com>
License: MIT License
Classifier: Programming Language :: Python :: 3
Classifier: License :: OSI Approved :: MIT License
Classifier: Operating System :: OS Independent
Classifier: Topic :: Software Development :: Libraries :: Python Modules
Requires-Python: >=3.7
License-File: LICENSE
Requires-Dist: mcp
Dynamic: license-file
